pricing_framework/__init__.py
pricing_framework/evaluation.py
pricing_framework/triage.py
ds_pricing_framework-0.1.14.dist-info/METADATA
ds_pricing_framework-0.1.14.dist-info/WHEEL
ds_pricing_framework-0.1.14.dist-info/top_level.txt
ds_pricing_framework-0.1.14.dist-info/RECORD
