Metadata-Version: 2.1
Name: ds-pricing-framework
Version: 0.1.14
Summary: Read the latest Real Python tutorials
Author-email: Kelsey Messonnier <kelsey@just.insure>
Keywords: feed,reader,tutorial
Classifier: License :: OSI Approved :: MIT License
Classifier: Programming Language :: Python
Classifier: Programming Language :: Python :: 3
Requires-Python: >=3.7
Requires-Dist: pandas
Requires-Dist: statsmodels
Requires-Dist: tabulate
Requires-Dist: numpy
Requires-Dist: matplotlib
